pydantic_uuid_model
